license.md
sprint_velocity/__init__.py
sprint_velocity/config.json
sprint_velocity/main.py
sprint_velocity/plot_matplolib.py
sprint_velocity/utils.py
sprint_velocity-1.0.5.dist-info/entry_points.txt
sprint_velocity-1.0.5.dist-info/LICENSE
sprint_velocity-1.0.5.dist-info/WHEEL
sprint_velocity-1.0.5.dist-info/METADATA
sprint_velocity-1.0.5.dist-info/RECORD
