Metadata-Version: 2.1
Name: sprint-velocity
Version: 1.0.5
Summary: Generating a Matplotlib plot to see the scrum velocity for a sprint.
Home-page: https://github.com/FelixTheC/jira_srcum_velocity
License: MIT
Author: FelixTheC
Author-email: fberndt87@gmail.com
Requires-Python: >=3.9,<4.0
Classifier: Environment :: Console
Classifier: Framework :: Matplotlib
Classifier: License :: OSI Approved :: MIT License
Classifier: Programming Language :: Python :: 3
Classifier: Programming Language :: Python :: 3 :: Only
Classifier: Programming Language :: Python :: 3.10
Classifier: Programming Language :: Python :: 3.9
Requires-Dist: matplotlib
Requires-Dist: pandas
Requires-Dist: pendulum
Requires-Dist: requests
Requires-Dist: strongtyping
Requires-Dist: typer[all]
